README.md
hi_tea.py
setup.py
teaxyz.egg-info/PKG-INFO
teaxyz.egg-info/SOURCES.txt
teaxyz.egg-info/dependency_links.txt
teaxyz.egg-info/entry_points.txt
teaxyz.egg-info/requires.txt
teaxyz.egg-info/top_level.txt