Metadata-Version: 2.1
Name: teaxyz
Version: 0.0.1
Summary: A simple package for https://app.tea.xyz/
Home-page: https://github.com/madest92/teaxyz
Author: Alex
Author-email: madest92@mail.com
Project-URL: Homepage, https://github.com/madest92/teaxyz
Project-URL: Source, https://github.com/madest92/teaxyz
Classifier: License :: OSI Approved :: MIT License
Classifier: Programming Language :: Python :: 3
Requires-Python: >=3.6
Requires-Dist: tea-xyz1
Requires-Dist: tea-xyz2
